erie_connect/__init__.py
erie_connect/client.py
erie_connect-0.4.4.dist-info/LICENSE
erie_connect-0.4.4.dist-info/METADATA
erie_connect-0.4.4.dist-info/WHEEL
erie_connect-0.4.4.dist-info/top_level.txt
erie_connect-0.4.4.dist-info/RECORD
