Metadata-Version: 2.1
Name: erie-connect
Version: 0.4.4
Summary: Unofficial Erie Connect cloud client to retrieve data from IQsoft 26 water softener
Home-page: https://github.com/tgebarowski/erie-connect
Author: Tomasz Gebarowski
Author-email: gebarowski@gmail.com
License: MIT
Platform: UNKNOWN
Classifier: Development Status :: 2 - Pre-Alpha
Classifier: License :: OSI Approved :: MIT License
Classifier: Programming Language :: Python
Classifier: Programming Language :: Python :: 3.5
Classifier: Programming Language :: Python :: 3.6
Classifier: Programming Language :: Python :: 3.7
License-File: LICENSE
Requires-Dist: requests (>=2.23.0)
Requires-Dist: simplejson (>=3.17.0)
